{
  "khoi": 7,
  "mon": "GDCD",
  "cauhoi": [
    {
      "id": 1,
      "dang": "Tự hào về truyền thống quê hương",
      "mucdo": "Nhận biết",
      "de": "Truyền thống quê hương là những giá trị gì?",
      "a": "Vật chất và tinh thần được hình thành trong lịch sử, được truyền từ thế hệ này sang thế hệ khác",
      "b": "Chỉ những phong tục tập quán cũ",
      "c": "Những thói quen xấu của địa phương",
      "d": "Các lễ hội hiện đại mới được tổ chức",
      "dap_an": "a",
      "giai_thich": "Truyền thống quê hương là những giá trị tốt đẹp về vật chất và tinh thần được hình thành trong lịch sử, được truyền từ thế hệ này sang thế hệ khác."
    },
    {
      "id": 2,
      "dang": "Tự hào về truyền thống quê hương",
      "mucdo": "Nhận biết",
      "de": "Hành vi nào sau đây thể hiện lòng tự hào về truyền thống quê hương?",
      "a": "Chê bai các món ăn địa phương",
      "b": "Không tham gia các lễ hội truyền thống",
      "c": "Giới thiệu với bạn bè về làng nghề truyền thống của quê mình",
      "d": "Xem thường các phong tục cũ",
      "dap_an": "c",
      "giai_thich": "Giới thiệu với bạn bè về làng nghề truyền thống thể hiện sự trân trọng và tự hào về giá trị quê hương."
    },
    {
      "id": 3,
      "dang": "Tự hào về truyền thống quê hương",
      "mucdo": "Nhận biết",
      "de": "Truyền thống nào sau đây thuộc về truyền thống quê hương?",
      "a": "Yêu nước, đoàn kết, hiếu học",
      "b": "Lười biếng, ỷ lại",
      "c": "Thờ ơ với cộng đồng",
      "d": "Sống khép kín, không giao lưu",
      "dap_an": "a",
      "giai_thich": "Yêu nước, đoàn kết, hiếu học là những truyền thống tốt đẹp của dân tộc và quê hương."
    },
    {
      "id": 4,
      "dang": "Tự hào về truyền thống quê hương",
      "mucdo": "Nhận biết",
      "de": "Việc làm nào góp phần giữ gìn truyền thống quê hương?",
      "a": "Phá bỏ các công trình kiến trúc cổ",
      "b": "Học nghề truyền thống của địa phương",
      "c": "Bỏ làng đi nơi khác sinh sống",
      "d": "Không quan tâm đến lễ hội bản địa",
      "dap_an": "b",
      "giai_thich": "Học nghề truyền thống vừa giữ gìn vừa phát huy giá trị văn hóa quê hương."
    },
    {
      "id": 5,
      "dang": "Tự hào về truyền thống quê hương",
      "mucdo": "Thông hiểu",
      "de": "Vì sao chúng ta cần tự hào về truyền thống quê hương?",
      "a": "Để thể hiện sự sành điệu, hiện đại",
      "b": "Vì đó là nền tảng tạo nên bản sắc và sức mạnh dân tộc",
      "c": "Để khoe khoang với người nước ngoài",
      "d": "Chỉ vì theo thói quen",
      "dap_an": "b",
      "giai_thich": "Truyền thống quê hương tạo nên bản sắc riêng, là nền tảng để phát triển và khẳng định giá trị dân tộc."
    },
    {
      "id": 6,
      "dang": "Tự hào về truyền thống quê hương",
      "mucdo": "Thông hiểu",
      "de": "Câu ca dao 'Dù ai đi ngược về xuôi, nhớ ngày giỗ Tổ mùng mười tháng ba' nhắc đến truyền thống nào?",
      "a": "Truyền thống yêu nước",
      "b": "Truyền thống hiếu học",
      "c": "Truyền thống uống nước nhớ nguồn",
      "d": "Truyền thống lao động",
      "dap_an": "c",
      "giai_thich": "Câu ca dao thể hiện lòng biết ơn tổ tiên, đúng với truyền thống uống nước nhớ nguồn."
    },
    {
      "id": 7,
      "dang": "Tự hào về truyền thống quê hương",
      "mucdo": "Thông hiểu",
      "de": "Học sinh có thể làm gì để phát huy truyền thống hiếu học của quê hương?",
      "a": "Chỉ học giỏi để được khen",
      "b": "Chăm chỉ học tập, giúp đỡ bạn cùng tiến bộ",
      "c": "Học qua loa cho xong",
      "d": "Không cần học vì đã có truyền thống",
      "dap_an": "b",
      "giai_thich": "Chăm chỉ học tập và giúp đỡ bạn bè là hành động thiết thực kế thừa truyền thống hiếu học."
    },
    {
      "id": 8,
      "dang": "Tự hào về truyền thống quê hương",
      "mucdo": "Vận dụng",
      "de": "Em sẽ làm gì khi thấy một số bạn trong lớp chê bai các điệu hát dân ca của địa phương là 'quê mùa'?",
      "a": "Mặc kệ vì không liên quan",
      "b": "Cùng các bạn chê để hòa đồng",
      "c": "Giải thích cho các bạn hiểu giá trị văn hóa và vẻ đẹp của dân ca",
      "d": "Báo cáo với thầy cô để phê bình các bạn",
      "dap_an": "c",
      "giai_thich": "Giải thích nhẹ nhàng giúp bạn hiểu giá trị văn hóa, khơi dậy lòng tự hào chứ không nên áp đặt."
    },
    {
      "id": 9,
      "dang": "Tự hào về truyền thống quê hương",
      "mucdo": "Vận dụng cao",
      "de": "Nhà trường phát động phong trào 'Giữ gìn làng nghề truyền thống', em sẽ tham gia bằng cách nào hiệu quả nhất?",
      "a": "Đăng ký học nghề và vận động bạn bè cùng tham gia tìm hiểu",
      "b": "Chỉ cần nộp bài viết về làng nghề",
      "c": "Kêu gọi phá bỏ làng nghề để xây khu công nghiệp",
      "d": "Không tham gia vì mất thời gian",
      "dap_an": "a",
      "giai_thich": "Học nghề và vận động bạn bè vừa giữ gìn truyền thống vừa lan tỏa, tạo sức trẻ cho làng nghề."
    },
    {
      "id": 10,
      "dang": "Tự hào về truyền thống quê hương",
      "mucdo": "Vận dụng cao",
      "de": "Em sẽ xử lý thế nào khi được giao nhiệm vụ thuyết trình về truyền thống quê hương trước lớp nhưng có bạn cố tình phá rối, nói những điều không hay?",
      "a": "Tranh cãi gay gắt với bạn",
      "b": "Bỏ dở bài thuyết trình",
      "c": "Bình tĩnh tiếp tục thuyết trình, sau đó gặp riêng bạn để chia sẻ và giải thích",
      "d": "Ra ngoài khóc và không nói gì",
      "dap_an": "c",
      "giai_thich": "Bình tĩnh thể hiện trách nhiệm và sự tự tin, sau đó khéo léo chia sẻ với bạn để bạn hiểu và tôn trọng truyền thống."
    },
    {
      "id": 11,
      "dang": "Quan tâm, cảm thông và chia sẻ",
      "mucdo": "Nhận biết",
      "de": "Quan tâm, cảm thông và chia sẻ có nghĩa là gì?",
      "a": "Chỉ quan tâm đến bản thân mình",
      "b": "Sẵn sàng giúp đỡ, thấu hiểu và đồng cảm với khó khăn của người khác",
      "c": "Làm thay mọi việc cho người khác",
      "d": "Chỉ chia sẻ khi được yêu cầu",
      "dap_an": "b",
      "giai_thich": "Đây là phẩm chất đạo đức, thể hiện sự đồng cảm và hành động giúp đỡ người khác."
    },
    {
      "id": 12,
      "dang": "Quan tâm, cảm thông và chia sẻ",
      "mucdo": "Nhận biết",
      "de": "Hành động nào thể hiện sự quan tâm đến bạn bè?",
      "a": "Hỏi thăm khi bạn bị ốm",
      "b": "Lờ đi khi bạn buồn",
      "c": "Nói xấu bạn khi bạn vắng mặt",
      "d": "Cô lập bạn trong lớp",
      "dap_an": "a",
      "giai_thich": "Hỏi thăm khi bạn ốm thể hiện sự quan tâm chân thành."
    },
    {
      "id": 13,
      "dang": "Quan tâm, cảm thông và chia sẻ",
      "mucdo": "Nhận biết",
      "de": "Biểu hiện của sự cảm thông là gì?",
      "a": "Phán xét người khác",
      "b": "Đặt mình vào vị trí của người khác để hiểu cảm xúc của họ",
      "c": "So sánh hoàn cảnh của mình với người khác",
      "d": "Tỏ ra thương hại",
      "dap_an": "b",
      "giai_thich": "Cảm thông là khả năng thấu hiểu cảm xúc của người khác từ chính trải nghiệm của họ."
    },
    {
      "id": 14,
      "dang": "Quan tâm, cảm thông và chia sẻ",
      "mucdo": "Nhận biết",
      "de": "Chia sẻ trong cuộc sống có thể là:",
      "a": "Chia sẻ vật chất và tinh thần",
      "b": "Chỉ chia sẻ tiền bạc",
      "c": "Chỉ động viên bằng lời nói",
      "d": "Không chia sẻ gì cả",
      "dap_an": "a",
      "giai_thich": "Chia sẻ bao gồm cả vật chất (quà, tiền) lẫn tinh thần (lời động viên, sự lắng nghe)."
    },
    {
      "id": 15,
      "dang": "Quan tâm, cảm thông và chia sẻ",
      "mucdo": "Thông hiểu",
      "de": "Vì sao cần quan tâm, cảm thông và chia sẻ với người khác?",
      "a": "Để được người khác nể sợ",
      "b": "Vì đó là nghĩa vụ bắt buộc",
      "c": "Giúp gắn kết tình người, xây dựng cộng đồng vững mạnh",
      "d": "Để tránh bị cô lập",
      "dap_an": "c",
      "giai_thich": "Sự quan tâm, chia sẻ tạo nên các mối quan hệ tốt đẹp, lan tỏa yêu thương trong xã hội."
    },
    {
      "id": 16,
      "dang": "Quan tâm, cảm thông và chia sẻ",
      "mucdo": "Thông hiểu",
      "de": "Trong tình huống bạn em bị điểm kém và rất buồn, em sẽ làm gì?",
      "a": "Kể với các bạn khác để cười",
      "b": "Mắng bạn vì không học bài",
      "c": "An ủi và cùng bạn xem lại bài để rút kinh nghiệm",
      "d": "Không quan tâm vì đó là việc của bạn",
      "dap_an": "c",
      "giai_thich": "An ủi và giúp đỡ bạn sửa sai thể hiện sự cảm thông và chia sẻ tích cực."
    },
    {
      "id": 17,
      "dang": "Quan tâm, cảm thông và chia sẻ",
      "mucdo": "Thông hiểu",
      "de": "Câu tục ngữ 'Lá lành đùm lá rách' nói về đức tính gì?",
      "a": "Tiết kiệm",
      "b": "Trung thực",
      "c": "Quan tâm, cảm thông và chia sẻ",
      "d": "Tự lập",
      "dap_an": "c",
      "giai_thich": "Câu tục ngữ khuyên người giàu có, khỏe mạnh nên giúp đỡ người nghèo khó, bất hạnh."
    },
    {
      "id": 18,
      "dang": "Quan tâm, cảm thông và chia sẻ",
      "mucdo": "Vận dụng",
      "de": "Em thấy một bạn trong lớp luôn bị các bạn khác trêu chọc vì nhà nghèo. Em sẽ làm gì?",
      "a": "Không làm gì vì sợ bị trêu theo",
      "b": "Cùng các bạn khác trêu bạn ấy cho vui",
      "c": "Bênh vực bạn ấy, giải thích cho các bạn hiểu việc trêu chọc là sai",
      "d": "Mách cô giáo để cô mắng các bạn",
      "dap_an": "c",
      "giai_thich": "Bênh vực và giải thích tế nhị vừa bảo vệ bạn, vừa giáo dục bạn bè, tránh đối đầu gay gắt."
    },
    {
      "id": 19,
      "dang": "Quan tâm, cảm thông và chia sẻ",
      "mucdo": "Vận dụng cao",
      "de": "Gia đình hàng xóm của em gặp hỏa hoạn, mất hết tài sản. Em có thể làm gì trong khả năng của một học sinh lớp 7?",
      "a": "Vận động bạn bè cùng quyên góp sách vở, quần áo cũ tặng họ",
      "b": "Đến xem và bình luận về đám cháy",
      "c": "Không liên quan vì mình còn nhỏ",
      "d": "Xin bố mẹ cho tiền nhiều để khoe",
      "dap_an": "a",
      "giai_thich": "Vận động quyên góp đồ dùng thiết thực với khả năng của học sinh là việc làm nhân văn, phù hợp lứa tuổi."
    },
    {
      "id": 20,
      "dang": "Quan tâm, cảm thông và chia sẻ",
      "mucdo": "Vận dụng cao",
      "de": "Em biết một người bạn cùng lớp có hoàn cảnh rất khó khăn nhưng bạn ấy rất tự ti, không dám nhận sự giúp đỡ. Em sẽ làm thế nào?",
      "a": "Ép bạn phải nhận quà",
      "b": "Lặng lẽ giúp đỡ qua thầy cô hoặc các hình thức kín đáo, đồng thời động viên tinh thần",
      "c": "Nói với cả lớp để mọi người cùng đến giúp",
      "d": "Bỏ mặc vì bạn không muốn nhận",
      "dap_an": "b",
      "giai_thich": "Tôn trọng lòng tự trọng của bạn, giúp đỡ kín đáo và khéo léo mới thực sự hiệu quả."
    },
    {
      "id": 21,
      "dang": "Học tập tự giác, tích cực",
      "mucdo": "Nhận biết",
      "de": "Học tập tự giác, tích cực là:",
      "a": "Học khi bị thầy cô nhắc nhở",
      "b": "Chủ động học, tìm tòi kiến thức mà không cần ai nhắc nhở",
      "c": "Chỉ học những môn mình thích",
      "d": "Học thuộc lòng mà không cần hiểu",
      "dap_an": "b",
      "giai_thich": "Tự giác, tích cực là chủ động, không phải bị ép buộc, và luôn cố gắng tìm hiểu."
    },
    {
      "id": 22,
      "dang": "Học tập tự giác, tích cực",
      "mucdo": "Nhận biết",
      "de": "Biểu hiện nào sau đây là học tập tự giác, tích cực?",
      "a": "Làm bài tập về nhà đầy đủ trước khi đến lớp",
      "b": "Chép bài của bạn khi không làm được",
      "c": "Học qua loa cho xong",
      "d": "Đợi đến sát giờ kiểm tra mới học",
      "dap_an": "a",
      "giai_thich": "Làm bài tập đầy đủ mà không cần ai nhắc là biểu hiện của tự giác học tập."
    },
    {
      "id": 23,
      "dang": "Học tập tự giác, tích cực",
      "mucdo": "Nhận biết",
      "de": "Việc làm nào KHÔNG thể hiện học tập tự giác, tích cực?",
      "a": "Tự đặt ra mục tiêu học tập cho bản thân",
      "b": "Nhờ bạn nhắc mỗi khi đến giờ học",
      "c": "Chuẩn bị bài mới trước khi đến lớp",
      "d": "Tìm đọc thêm sách tham khảo",
      "dap_an": "b",
      "giai_thich": "Nhờ bạn nhắc không phải là tự giác mà là phụ thuộc."
    },
    {
      "id": 24,
      "dang": "Học tập tự giác, tích cực",
      "mucdo": "Nhận biết",
      "de": "Lợi ích của học tập tự giác, tích cực là gì?",
      "a": "Mất nhiều thời gian hơn",
      "b": "Kết quả học tập cao, hiểu bài sâu, rèn tính chủ động",
      "c": "Luôn căng thẳng, mệt mỏi",
      "d": "Dễ bị bạn bè xa lánh",
      "dap_an": "b",
      "giai_thich": "Học tập tự giác giúp tiếp thu kiến thức tốt và hình thành phẩm chất tốt."
    },
    {
      "id": 25,
      "dang": "Học tập tự giác, tích cực",
      "mucdo": "Thông hiểu",
      "de": "Vì sao học sinh cần học tập tự giác, tích cực?",
      "a": "Vì đó là yêu cầu của cha mẹ",
      "b": "Để tránh bị phạt",
      "c": "Giúp chủ động chiếm lĩnh kiến thức, chuẩn bị cho tương lai",
      "d": "Để được thầy cô yêu quý hơn",
      "dap_an": "c",
      "giai_thich": "Tự giác học tập giúp học sinh làm chủ việc học, nâng cao hiệu quả và phát triển bản thân."
    },
    {
      "id": 26,
      "dang": "Học tập tự giác, tích cực",
      "mucdo": "Thông hiểu",
      "de": "Bạn Hùng luôn làm bài tập đầy đủ, lại chủ động hỏi thầy những chỗ chưa hiểu. Theo em, Hùng là người thế nào?",
      "a": "Học tập thụ động",
      "b": "Học tập tự giác, tích cực",
      "c": "Học quá nhiều không cần thiết",
      "d": "Khoe khoang",
      "dap_an": "b",
      "giai_thich": "Hùng thể hiện sự chủ động, đó là tự giác, tích cực."
    },
    {
      "id": 27,
      "dang": "Học tập tự giác, tích cực",
      "mucdo": "Vận dụng",
      "de": "Em đã lên kế hoạch học tập nhưng hôm nay bạn rủ đi chơi game. Em sẽ làm gì?",
      "a": "Bỏ kế hoạch để đi chơi",
      "b": "Học nhanh qua loa rồi đi",
      "c": "Từ chối khéo và hẹn bạn dịp khác sau khi học xong",
      "d": "Đi chơi nhưng mang sách theo",
      "dap_an": "c",
      "giai_thich": "Từ chối khéo vừa giữ kế hoạch vừa không mất lòng bạn."
    },
    {
      "id": 28,
      "dang": "Học tập tự giác, tích cực",
      "mucdo": "Vận dụng",
      "de": "Em thấy bạn Lan thường xuyên chép bài của bạn khác. Em sẽ khuyên Lan điều gì?",
      "a": "Lan nên tự làm bài để hiểu bài hơn",
      "b": "Đừng làm nữa kẻo bị cô phát hiện",
      "c": "Chép thì cũng được, không sao",
      "d": "Nên nhờ bạn làm hộ",
      "dap_an": "a",
      "giai_thich": "Khuyên bạn tự làm là giúp bạn học tập tự giác, hiểu bài thực sự."
    },
    {
      "id": 29,
      "dang": "Học tập tự giác, tích cực",
      "mucdo": "Vận dụng cao",
      "de": "Em đang gặp khó khăn trong môn Toán, không tự học được. Giải pháp tốt nhất để rèn tính tự giác là:",
      "a": "Tự lập thời gian biểu, chia nhỏ bài khó, tìm bạn học nhóm",
      "b": "Nhờ bố mẹ luôn ngồi cạnh giám sát",
      "c": "Bỏ qua môn đó vì không có năng khiếu",
      "d": "Chỉ học thuộc công thức mà không làm bài tập",
      "dap_an": "a",
      "giai_thich": "Tự lập kế hoạch, chia nhỏ và hợp tác giúp vượt qua khó khăn một cách tự giác và bền vững."
    },
    {
      "id": 30,
      "dang": "Học tập tự giác, tích cực",
      "mucdo": "Vận dụng cao",
      "de": "Nhà trường triển khai hình thức 'Học qua dự án' yêu cầu học sinh tự nghiên cứu. Với một bạn thường thụ động, em sẽ khuyên bạn ấy thế nào để thích ứng?",
      "a": "Nhờ bố mẹ làm hộ",
      "b": "Chép bài của nhóm khác",
      "c": "Bắt đầu từ việc nhỏ như tự tìm tài liệu, đặt câu hỏi, sau đó dần mở rộng",
      "d": "Xin chuyển sang lớp khác không làm dự án",
      "dap_an": "c",
      "giai_thich": "Khuyên bạn bắt đầu từ bước nhỏ, từng bước rèn tự giác, phù hợp tâm lý học sinh."
    },
    {
      "id": 31,
      "dang": "Giữ chữ tín",
      "mucdo": "Nhận biết",
      "de": "Giữ chữ tín là gì?",
      "a": "Nói gì cũng được, không cần thực hiện",
      "b": "Coi trọng lòng tin của mọi người đối với mình, biết giữ lời hứa",
      "c": "Hứa đại để người khác vui lòng",
      "d": "Chỉ giữ lời với người lớn",
      "dap_an": "b",
      "giai_thich": "Giữ chữ tín là tôn trọng lời hứa và trách nhiệm của bản thân với người khác."
    },
    {
      "id": 32,
      "dang": "Giữ chữ tín",
      "mucdo": "Nhận biết",
      "de": "Hành vi nào thể hiện giữ chữ tín?",
      "a": "Hứa cho bạn mượn sách và đúng hẹn mang đến",
      "b": "Hứa sẽ giúp nhưng lại quên",
      "c": "Nói dối để qua mặt bố mẹ",
      "d": "Cam kết không làm bài tập về nhà",
      "dap_an": "a",
      "giai_thich": "Đúng hẹn mang sách cho bạn mượn là giữ lời hứa."
    },
    {
      "id": 33,
      "dang": "Giữ chữ tín",
      "mucdo": "Nhận biết",
      "de": "Người không giữ chữ tín sẽ:",
      "a": "Được mọi người tin yêu",
      "b": "Mất lòng tin của người khác",
      "c": "Dễ thành công trong công việc",
      "d": "Được đề cao trong xã hội",
      "dap_an": "b",
      "giai_thich": "Không giữ chữ tín sẽ làm mất uy tín và lòng tin từ người khác."
    },
    {
      "id": 34,
      "dang": "Giữ chữ tín",
      "mucdo": "Nhận biết",
      "de": "Câu thành ngữ nào nói về chữ tín?",
      "a": "Ăn quả nhớ kẻ trồng cây",
      "b": "Lời nói đôi điều, làm sao cho vừa",
      "c": "Chữ tín quý hơn vàng",
      "d": "Có công mài sắt có ngày nên kim",
      "dap_an": "c",
      "giai_thich": "Câu 'Chữ tín quý hơn vàng' khẳng định giá trị của lòng tin."
    },
    {
      "id": 35,
      "dang": "Giữ chữ tín",
      "mucdo": "Thông hiểu",
      "de": "Vì sao phải giữ chữ tín trong học tập và cuộc sống?",
      "a": "Để được điểm cao",
      "b": "Để bạn bè và thầy cô tin tưởng, tạo dựng uy tín cá nhân",
      "c": "Để tránh bị phạt",
      "d": "Vì đó là luật bắt buộc",
      "dap_an": "b",
      "giai_thich": "Giữ chữ tín xây dựng niềm tin, uy tín và các mối quan hệ bền vững."
    },
    {
      "id": 36,
      "dang": "Giữ chữ tín",
      "mucdo": "Thông hiểu",
      "de": "Hứa mà không làm thì gây hậu quả gì?",
      "a": "Mọi người vẫn tin tưởng",
      "b": "Không ảnh hưởng gì",
      "c": "Làm giảm uy tín, gây thất vọng cho người khác",
      "d": "Được khen là dám hứa",
      "dap_an": "c",
      "giai_thich": "Không thực hiện lời hứa làm người khác thất vọng, bản thân mất uy tín."
    },
    {
      "id": 37,
      "dang": "Giữ chữ tín",
      "mucdo": "Thông hiểu",
      "de": "Trong tình huống đã hứa giúp bạn một việc nhưng đến lúc thực hiện lại bị ốm, em nên làm gì?",
      "a": "Để bạn tự xoay sở",
      "b": "Cố gắng làm bằng được",
      "c": "Gọi điện xin lỗi bạn và tìm cách sắp xếp lại hoặc nhờ người khác giúp",
      "d": "Lờ đi coi như chưa hứa",
      "dap_an": "c",
      "giai_thich": "Giữ chữ tín cũng cần linh hoạt, thông báo và tìm giải pháp thay thế."
    },
    {
      "id": 38,
      "dang": "Giữ chữ tín",
      "mucdo": "Vận dụng",
      "de": "Em mượn sách của bạn và hứa trả sau 2 ngày. Nhưng chưa kịp đọc xong, em nên:",
      "a": "Giữ thêm vài hôm cho đọc xong",
      "b": "Trả đúng hẹn, sau đó mượn lại nếu bạn đồng ý",
      "c": "Ném trả sách vào bàn bạn",
      "d": "Làm rách sách rồi im lặng",
      "dap_an": "b",
      "giai_thich": "Trả đúng hẹn thể hiện chữ tín, sau đó hỏi lại là phù hợp."
    },
    {
      "id": 39,
      "dang": "Giữ chữ tín",
      "mucdo": "Vận dụng cao",
      "de": "Em được phân công làm nhóm trưởng, nhóm có bạn rất hay hứa nhưng không làm. Để giữ chữ tín với nhóm và giúp bạn, em sẽ:",
      "a": "Làm luôn phần của bạn ấy",
      "b": "Không giao việc cho bạn ấy nữa",
      "c": "Trao đổi riêng, nhắc nhở tế nhị và giao việc nhỏ để bạn tập giữ lời hứa",
      "d": "Mách cô để cô phạt bạn",
      "dap_an": "c",
      "giai_thich": "Vừa giữ trách nhiệm nhóm, vừa tạo cơ hội để bạn thay đổi, vừa giúp bạn hiểu về chữ tín."
    },
    {
      "id": 40,
      "dang": "Giữ chữ tín",
      "mucdo": "Vận dụng cao",
      "de": "Một người bạn thân rủ em trốn học đi chơi và yêu cầu em giữ bí mật với bố mẹ. Em sẽ xử lý thế nào để vừa giữ chữ tín với bạn, vừa đúng đạo đức?",
      "a": "Đi chơi và giữ bí mật",
      "b": "Từ chối và hứa sẽ không kể với ai, nhưng khuyên bạn không nên trốn học",
      "c": "Nói ngay với bố mẹ bạn",
      "d": "Mặc kệ, không quan tâm",
      "dap_an": "b",
      "giai_thich": "Giữ lời hứa không kể nhưng từ chối việc sai và khuyên bạn là cách xử lý tinh tế, vẹn cả đôi đường."
    },
    {
      "id": 41,
      "dang": "Bảo tồn di sản văn hóa",
      "mucdo": "Nhận biết",
      "de": "Di sản văn hóa bao gồm những gì?",
      "a": "Di sản văn hóa phi vật thể và di sản văn hóa vật thể",
      "b": "Chỉ có các lễ hội",
      "c": "Chỉ các công trình kiến trúc",
      "d": "Chỉ các món ăn truyền thống",
      "dap_an": "a",
      "giai_thich": "Di sản văn hóa được phân thành hai loại chính: vật thể và phi vật thể."
    },
    {
      "id": 42,
      "dang": "Bảo tồn di sản văn hóa",
      "mucdo": "Nhận biết",
      "de": "Ví dụ nào là di sản văn hóa vật thể?",
      "a": "Vịnh Hạ Long",
      "b": "Hát Xoan",
      "c": "Tín ngưỡng thờ cúng Hùng Vương",
      "d": "Nghệ thuật múa rối nước",
      "dap_an": "a",
      "giai_thich": "Vịnh Hạ Long là danh lam thắng cảnh, thuộc di sản vật thể."
    },
    {
      "id": 43,
      "dang": "Bảo tồn di sản văn hóa",
      "mucdo": "Nhận biết",
      "de": "Ví dụ nào là di sản văn hóa phi vật thể?",
      "a": "Phố cổ Hội An",
      "b": "Thánh địa Mỹ Sơn",
      "c": "Nhã nhạc cung đình Huế",
      "d": "Vườn quốc gia Phong Nha – Kẻ Bàng",
      "dap_an": "c",
      "giai_thich": "Nhã nhạc cung đình Huế là loại hình nghệ thuật âm nhạc, thuộc phi vật thể."
    },
    {
      "id": 44,
      "dang": "Bảo tồn di sản văn hóa",
      "mucdo": "Nhận biết",
      "de": "Hành vi nào góp phần bảo tồn di sản văn hóa?",
      "a": "Viết chữ lên tường đền, chùa",
      "b": "Tham gia lễ hội truyền thống",
      "c": "Đập phá hiện vật trong bảo tàng",
      "d": "Xả rác bừa bãi tại khu di tích",
      "dap_an": "b",
      "giai_thich": "Tham gia lễ hội giúp gìn giữ và phát huy giá trị văn hóa phi vật thể."
    },
    {
      "id": 45,
      "dang": "Bảo tồn di sản văn hóa",
      "mucdo": "Thông hiểu",
      "de": "Vì sao phải bảo tồn di sản văn hóa?",
      "a": "Vì chúng rất cổ kính",
      "b": "Vì đó là tài sản riêng của địa phương",
      "c": "Làm giàu cho thế hệ sau",
      "d": "Giữ gìn bản sắc dân tộc, giáo dục truyền thống, phát triển du lịch",
      "dap_an": "d",
      "giai_thich": "Bảo tồn di sản vì nhiều ý nghĩa: văn hóa, lịch sử, giáo dục và kinh tế."
    },
    {
      "id": 46,
      "dang": "Bảo tồn di sản văn hóa",
      "mucdo": "Thông hiểu",
      "de": "Trong tình huống thấy một nhóm thanh niên đang bẻ cành cây tại khu di tích lịch sử, em nên làm gì?",
      "a": "Làm ngơ",
      "b": "Cùng tham gia cho vui",
      "c": "Nhẹ nhàng nhắc nhở hoặc báo cho người quản lý di tích",
      "d": "Chụp ảnh đăng lên mạng",
      "dap_an": "c",
      "giai_thich": "Nhắc nhở hoặc báo quản lý là hành động có trách nhiệm bảo vệ di sản."
    },
    {
      "id": 47,
      "dang": "Bảo tồn di sản văn hóa",
      "mucdo": "Thông hiểu",
      "de": "Tại sao học sinh cần tìm hiểu về di sản văn hóa?",
      "a": "Để có điểm cao trong môn Lịch sử",
      "b": "Để hiểu và tự hào về cội nguồn, có ý thức bảo vệ",
      "c": "Để sau này làm hướng dẫn viên du lịch",
      "d": "Để khoe với bạn bè",
      "dap_an": "b",
      "giai_thich": "Hiểu biết về di sản nuôi dưỡng lòng tự hào và trách nhiệm công dân."
    },
    {
      "id": 48,
      "dang": "Bảo tồn di sản văn hóa",
      "mucdo": "Vận dụng",
      "de": "Trường em tổ chức đi tham quan một di tích lịch sử nhưng một số bạn lại có ý định khắc tên lên tường. Em sẽ làm gì?",
      "a": "Không nói gì, sợ mất lòng",
      "b": "Khuyên các bạn không nên làm vậy, giải thích đó là phá hoại di sản",
      "c": "Khắc tên mình còn to hơn",
      "d": "Báo ngay cho cô giáo chủ nhiệm",
      "dap_an": "b",
      "giai_thich": "Trước hết khuyên giải, nếu không được mới báo giáo viên, thể hiện trách nhiệm và khéo léo."
    },
    {
      "id": 49,
      "dang": "Bảo tồn di sản văn hóa",
      "mucdo": "Vận dụng cao",
      "de": "Em được giao viết bài giới thiệu về một di sản văn hóa địa phương. Làm thế nào để bài viết của em vừa hấp dẫn vừa thực sự góp phần quảng bá di sản?",
      "a": "Chép từ Wikipedia",
      "b": "Tìm hiểu kỹ, kết hợp ảnh tự chụp, những câu chuyện dân gian và liên hệ thực tế cuộc sống hiện nay",
      "c": "Chỉ viết theo trí nhớ",
      "d": "Kể chuyện ma ở di tích để gây tò mò",
      "dap_an": "b",
      "giai_thich": "Tìm hiểu kỹ lưỡng, có hình ảnh thực tế và câu chuyện chân thực giúp bài viết sống động, có giá trị quảng bá."
    },
    {
      "id": 50,
      "dang": "Bảo tồn di sản văn hóa",
      "mucdo": "Vận dụng cao",
      "de": "Có ý kiến cho rằng: 'Di sản văn hóa chỉ cần bảo tồn, không cần phát triển vì thay đổi sẽ mất đi giá trị gốc'. Em đồng tình không và vì sao?",
      "a": "Đồng tình, giữ nguyên mới là quý",
      "b": "Không đồng tình, vì cần kết hợp bảo tồn và phát huy giá trị phù hợp với bối cảnh hiện đại",
      "c": "Không quan tâm",
      "d": "Chỉ đồng tình một nửa",
      "dap_an": "b",
      "giai_thich": "Bảo tồn không có nghĩa là đông cứng mà cần phát huy giá trị trong đời sống đương đại, làm giàu thêm."
    },
    {
      "id": 51,
      "dang": "Ứng phó với tâm lí căng thẳng",
      "mucdo": "Nhận biết",
      "de": "Biểu hiện nào cho thấy một người đang bị căng thẳng tâm lí?",
      "a": "Vui vẻ, hòa đồng",
      "b": "Ăn ngon, ngủ kỹ",
      "c": "Đau đầu, mất ngủ, lo lắng kéo dài",
      "d": "Tập thể dục đều đặn",
      "dap_an": "c",
      "giai_thich": "Đau đầu, mất ngủ, lo lắng kéo dài là triệu chứng phổ biến của căng thẳng."
    },
    {
      "id": 52,
      "dang": "Ứng phó với tâm lí căng thẳng",
      "mucdo": "Nhận biết",
      "de": "Nguyên nhân nào thường gây căng thẳng tâm lí ở học sinh?",
      "a": "Đi du lịch",
      "b": "Áp lực thi cử, điểm số",
      "c": "Được khen thưởng",
      "d": "Tham gia hoạt động ngoại khóa",
      "dap_an": "b",
      "giai_thich": "Áp lực học tập, thi cử là một trong những nguyên nhân chính gây căng thẳng cho học sinh."
    },
    {
      "id": 53,
      "dang": "Ứng phó với tâm lí căng thẳng",
      "mucdo": "Nhận biết",
      "de": "Cách ứng phó tích cực với căng thẳng là:",
      "a": "Bỏ ăn, bỏ ngủ",
      "b": "La hét, đập phá đồ đạc",
      "c": "Chia sẻ với người thân, tập thể dục, hít thở sâu",
      "d": "Thu mình, không nói chuyện",
      "dap_an": "c",
      "giai_thich": "Chia sẻ, vận động, thư giãn là những cách lành mạnh để giảm căng thẳng."
    },
    {
      "id": 54,
      "dang": "Ứng phó với tâm lí căng thẳng",
      "mucdo": "Nhận biết",
      "de": "Khi căng thẳng, học sinh nên tránh hành vi nào sau đây?",
      "a": "Nghe nhạc nhẹ",
      "b": "Viết nhật ký",
      "c": "Tự làm hại bản thân",
      "d": "Đi dạo",
      "dap_an": "c",
      "giai_thich": "Tự làm hại bản thân là hành vi rất nguy hiểm, cần tránh tuyệt đối."
    },
    {
      "id": 55,
      "dang": "Ứng phó với tâm lí căng thẳng",
      "mucdo": "Thông hiểu",
      "de": "Vì sao cần học cách ứng phó với căng thẳng?",
      "a": "Để không bao giờ bị căng thẳng",
      "b": "Để căng thẳng biến mất hoàn toàn",
      "c": "Để duy trì sức khỏe thể chất và tinh thần, nâng cao chất lượng cuộc sống",
      "d": "Để được mọi người thương hại",
      "dap_an": "c",
      "giai_thich": "Ứng phó tốt giúp bảo vệ sức khỏe, tránh những hậu quả tiêu cực."
    },
    {
      "id": 56,
      "dang": "Ứng phó với tâm lí căng thẳng",
      "mucdo": "Thông hiểu",
      "de": "Bạn em thường xuyên lo lắng, sợ hãi trước các kỳ thi dù đã học bài. Em nên khuyên bạn điều gì?",
      "a": "Bỏ thi để khỏi lo",
      "b": "Học thêm nhiều hơn nữa",
      "c": "Thực hành thư giãn, hít thở sâu, ngủ đủ giấc và chia sẻ với bố mẹ",
      "d": "Dùng thuốc an thần",
      "dap_an": "c",
      "giai_thich": "Thư giãn, chia sẻ và sinh hoạt điều độ giúp giảm lo âu thi cử."
    },
    {
      "id": 57,
      "dang": "Ứng phó với tâm lí căng thẳng",
      "mucdo": "Vận dụng",
      "de": "Em vừa bị điểm kém và bố mẹ rầy la. Em cảm thấy rất căng thẳng. Em sẽ làm gì trước?",
      "a": "Cãi lại bố mẹ",
      "b": "Bỏ nhà đi bụi",
      "c": "Bình tĩnh, hít thở sâu, sau đó xin lỗi và hứa cố gắng",
      "d": "Khóc thật to",
      "dap_an": "c",
      "giai_thich": "Bình tĩnh và nói chuyện tích cực giúp giải quyết vấn đề thay vì làm căng thẳng thêm."
    },
    {
      "id": 58,
      "dang": "Ứng phó với tâm lí căng thẳng",
      "mucdo": "Vận dụng",
      "de": "Em thấy bạn thân có dấu hiệu trầm cảm, luôn thu mình và muốn nghỉ học. Hành động nào phù hợp nhất?",
      "a": "Mặc kệ, không liên quan",
      "b": "Trêu bạn để bạn vui lên",
      "c": "Lắng nghe, động viên và báo với giáo viên hoặc phụ huynh",
      "d": "Rủ bạn bỏ học đi chơi",
      "dap_an": "c",
      "giai_thich": "Hỗ trợ tinh thần và báo người lớn có chuyên môn là cách an toàn, hiệu quả."
    },
    {
      "id": 59,
      "dang": "Ứng phó với tâm lí căng thẳng",
      "mucdo": "Vận dụng cao",
      "de": "Em đang trong giai đoạn ôn thi học kỳ, thời gian biểu kín mít. Em bắt đầu đau đầu, mất ngủ. Giải pháp tối ưu nhất cho em lúc này là:",
      "a": "Ngừng học hoàn toàn, nghỉ ngơi vài ngày",
      "b": "Tự điều chỉnh thời gian biểu, sắp xếp giờ nghỉ ngơi hợp lý, tập thể dục nhẹ và ăn uống đủ chất",
      "c": "Uống nhiều cà phê để thức học",
      "d": "Học thâu đêm để bù lại",
      "dap_an": "b",
      "giai_thich": "Cân bằng học và nghỉ, chăm sóc sức khỏe là chiến lược bền vững, vừa giảm căng thẳng vừa đạt hiệu quả cao."
    },
    {
      "id": 60,
      "dang": "Ứng phó với tâm lí căng thẳng",
      "mucdo": "Vận dụng cao",
      "de": "Một người bạn tâm sự với em rằng bạn ấy nghĩ đến việc tự tử vì quá căng thẳng. Em sẽ:",
      "a": "Giữ kín chuyện này, hứa không nói ai",
      "b": "Lờ đi vì sợ trách nhiệm",
      "c": "Lập tức báo ngay cho người lớn tin cậy (cha mẹ bạn, giáo viên) và ở bên an ủi bạn",
      "d": "Khuyên bạn lên mạng tìm cách giải quyết",
      "dap_an": "c",
      "giai_thich": "Đây là tình huống khẩn cấp, cần sự can thiệp của người lớn, không thể giữ kín hay tự giải quyết."
    },
    {
      "id": 61,
      "dang": "Phòng, chống bạo lực học đường",
      "mucdo": "Nhận biết",
      "de": "Bạo lực học đường là gì?",
      "a": "Những xung đột nhẹ giữa học sinh",
      "b": "Hành vi gây tổn thương về thể chất, tinh thần giữa học sinh với nhau trong môi trường giáo dục",
      "c": "Cãi nhau giữa giáo viên và học sinh",
      "d": "Đánh nhau ngoài đường phố",
      "dap_an": "b",
      "giai_thich": "Bạo lực học đường xảy ra trong khuôn viên trường học hoặc liên quan đến học sinh, giáo viên."
    },
    {
      "id": 62,
      "dang": "Phòng, chống bạo lực học đường",
      "mucdo": "Nhận biết",
      "de": "Hình thức nào dưới đây là bạo lực học đường?",
      "a": "Tranh luận sôi nổi về bài tập",
      "b": "Chê bai ngoại hình bạn trước lớp",
      "c": "Giúp bạn làm bài tập",
      "d": "Đọc sách cùng bạn",
      "dap_an": "b",
      "giai_thich": "Chê bai, lăng mạ là bạo lực tinh thần, một dạng bạo lực học đường."
    },
    {
      "id": 63,
      "dang": "Phòng, chống bạo lực học đường",
      "mucdo": "Nhận biết",
      "de": "Nguyên nhân nào dẫn đến bạo lực học đường?",
      "a": "Tình bạn thân thiết",
      "b": "Mâu thuẫn, thiếu kỹ năng giải quyết xung đột",
      "c": "Được điểm cao",
      "d": "Tham gia câu lạc bộ",
      "dap_an": "b",
      "giai_thich": "Mâu thuẫn không được giải quyết đúng cách là nguyên nhân chính."
    },
    {
      "id": 64,
      "dang": "Phòng, chống bạo lực học đường",
      "mucdo": "Nhận biết",
      "de": "Hậu quả của bạo lực học đường đối với nạn nhân là:",
      "a": "Tự tin hơn",
      "b": "Sợ hãi, trầm cảm, chán học",
      "c": "Được bạn bè nể phục",
      "d": "Thành tích học tập tăng",
      "dap_an": "b",
      "giai_thich": "Hậu quả tâm lý và thể chất rất nặng nề, ảnh hưởng lâu dài."
    },
    {
      "id": 65,
      "dang": "Phòng, chống bạo lực học đường",
      "mucdo": "Thông hiểu",
      "de": "Khi chứng kiến một vụ bạo lực học đường, em nên làm gì?",
      "a": "Hò reo, cổ vũ",
      "b": "Bỏ đi, không liên quan",
      "c": "Can ngăn nếu an toàn, hoặc báo ngay cho thầy cô, người lớn",
      "d": "Quay video đăng lên mạng",
      "dap_an": "c",
      "giai_thich": "Can ngăn hoặc báo cáo là hành động có trách nhiệm, giúp ngăn chặn bạo lực."
    },
    {
      "id": 66,
      "dang": "Phòng, chống bạo lực học đường",
      "mucdo": "Thông hiểu",
      "de": "Vì sao học sinh cần được trang bị kỹ năng phòng, chống bạo lực học đường?",
      "a": "Để có thể tự đánh trả lại",
      "b": "Để trở nên mạnh mẽ, không sợ ai",
      "c": "Để bảo vệ bản thân và bạn bè, góp phần xây dựng môi trường học đường an toàn",
      "d": "Để gây sự với người khác",
      "dap_an": "c",
      "giai_thich": "Kỹ năng giúp tự bảo vệ và tạo môi trường lành mạnh."
    },
    {
      "id": 67,
      "dang": "Phòng, chống bạo lực học đường",
      "mucdo": "Vận dụng",
      "de": "Em bị một nhóm bạn trong trường thường xuyên trêu chọc, lấy đồ và dọa đánh. Em nên làm gì đầu tiên?",
      "a": "Rủ bạn bè đánh lại",
      "b": "Im lặng chịu đựng",
      "c": "Kể lại với bố mẹ và thầy cô, nhờ can thiệp",
      "d": "Nghỉ học để tránh",
      "dap_an": "c",
      "giai_thich": "Chia sẻ với người lớn tin cậy là cách an toàn và hiệu quả nhất."
    },
    {
      "id": 68,
      "dang": "Phòng, chống bạo lực học đường",
      "mucdo": "Vận dụng",
      "de": "Em thấy hai bạn trong lớp đánh nhau, một bạn bị chảy máu môi. Việc đầu tiên em nên làm:",
      "a": "Chạy đi gọi giáo viên hoặc bảo vệ",
      "b": "Xông vào can ngăn bằng tay không",
      "c": "Đứng xem",
      "d": "Chụp ảnh đăng Facebook",
      "dap_an": "a",
      "giai_thich": "Gọi người lớn là cách an toàn và nhanh chóng nhất để ngăn chặn vụ việc."
    },
    {
      "id": 69,
      "dang": "Phòng, chống bạo lực học đường",
      "mucdo": "Vận dụng cao",
      "de": "Em và một bạn có xích mích nhỏ. Hôm sau bạn ấy rủ thêm mấy người chặn em sau trường. Em sẽ làm thế nào để giải quyết tình huống này một cách thông minh?",
      "a": "Đánh trả liều mạng",
      "b": "Nhờ bạn khác đến đánh hộ",
      "c": "Bình tĩnh, tìm cách bỏ chạy đến nơi đông người, sau đó báo với thầy cô và gia đình",
      "d": "Cãi lại và thách thức",
      "dap_an": "c",
      "giai_thich": "Tránh xung đột trực tiếp, ưu tiên an toàn tính mạng, sau đó báo người lớn."
    },
    {
      "id": 70,
      "dang": "Phòng, chống bạo lực học đường",
      "mucdo": "Vận dụng cao",
      "de": "Là lớp trưởng, em phát hiện một nhóm học sinh khác lớp có ý định đánh một bạn trong lớp mình. Em sẽ tổ chức ngăn chặn bằng cách nào khôn khéo nhất?",
      "a": "Hô hào cả lớp cầm gậy ra đe dọa",
      "b": "Báo cáo nhanh với giáo viên chủ nhiệm và bảo vệ nhà trường",
      "c": "Rủ bạn bị đánh trốn học",
      "d": "Tự mình ra nói chuyện, rủ nhóm kia đi uống nước để giải hòa",
      "dap_an": "b",
      "giai_thich": "Với tư cách học sinh, việc báo với giáo viên là đúng quy trình và an toàn nhất, tránh tự giải quyết có thể gây nguy hiểm."
    },
    {
      "id": 71,
      "dang": "Quản lí tiền",
      "mucdo": "Nhận biết",
      "de": "Quản lí tiền hiệu quả là:",
      "a": "Tiêu hết số tiền có",
      "b": "Chi tiêu hợp lý, tiết kiệm, có kế hoạch",
      "c": "Vay mượn để tiêu",
      "d": "Không bao giờ tiêu tiền",
      "dap_an": "b",
      "giai_thich": "Quản lý tiền là biết cách chi tiêu, tiết kiệm và lập kế hoạch tài chính."
    },
    {
      "id": 72,
      "dang": "Quản lí tiền",
      "mucdo": "Nhận biết",
      "de": "Việc làm nào thể hiện quản lí tiền chưa tốt?",
      "a": "Ghi chép các khoản chi tiêu",
      "b": "Mua đồ không cần thiết khi thấy bạn bè có",
      "c": "Đặt mục tiêu tiết kiệm",
      "d": "So sánh giá trước khi mua",
      "dap_an": "b",
      "giai_thich": "Mua theo phong trào, không cân nhắc là lãng phí, quản lý kém."
    },
    {
      "id": 73,
      "dang": "Quản lí tiền",
      "mucdo": "Nhận biết",
      "de": "Học sinh lớp 7 có thể tiết kiệm tiền bằng cách nào?",
      "a": "Xin tiền bố mẹ nhiều hơn",
      "b": "Bỏ ống heo từ tiền ăn sáng hoặc tiền thưởng",
      "c": "Đi làm thêm ngoài giờ",
      "d": "Vay tiền bạn để tiết kiệm",
      "dap_an": "b",
      "giai_thich": "Tiết kiệm từ các khoản nhỏ hàng ngày là phù hợp với lứa tuổi."
    },
    {
      "id": 74,
      "dang": "Quản lí tiền",
      "mucdo": "Nhận biết",
      "de": "Mục đích của việc quản lí tiền là:",
      "a": "Để trở nên giàu có",
      "b": "Để có thể mua được thứ mình thích bất cứ lúc nào",
      "c": "Để chủ động tài chính, tránh lãng phí, tạo thói quen tốt",
      "d": "Để không phải xin tiền bố mẹ",
      "dap_an": "c",
      "giai_thich": "Quản lý tiền giúp làm chủ chi tiêu, hình thành thói quen tốt cho tương lai."
    },
    {
      "id": 75,
      "dang": "Quản lí tiền",
      "mucdo": "Thông hiểu",
      "de": "Vì sao học sinh cần học cách quản lí tiền từ sớm?",
      "a": "Vì có nhiều tiền",
      "b": "Để sau này không phải làm việc",
      "c": "Để rèn tính tự lập, tránh lãng phí và có kỹ năng sống cần thiết",
      "d": "Để tiêu tiền thoải mái hơn",
      "dap_an": "c",
      "giai_thich": "Quản lý tiền sớm là kỹ năng sống quan trọng, giúp tự lập và tránh nợ nần sau này."
    },
    {
      "id": 76,
      "dang": "Quản lí tiền",
      "mucdo": "Thông hiểu",
      "de": "Nếu được bố mẹ cho 100.000 đồng để tiêu trong tuần, em nên lên kế hoạch thế nào?",
      "a": "Tiêu hết vào ngày đầu để sướng",
      "b": "Chia nhỏ cho các ngày, ưu tiên nhu cầu thiết yếu trước",
      "c": "Để dành hết, không tiêu gì",
      "d": "Mượn thêm để tiêu phung phí",
      "dap_an": "b",
      "giai_thich": "Chia đều và ưu tiên nhu cầu chính là quản lý tiền hiệu quả."
    },
    {
      "id": 77,
      "dang": "Quản lí tiền",
      "mucdo": "Vận dụng",
      "de": "Em có 200.000 đồng và muốn mua cả sách tham khảo (giá 120.000đ) và một món đồ chơi (giá 100.000đ). Em nên quyết định thế nào?",
      "a": "Mua cả hai, rồi xin bố mẹ thêm",
      "b": "Mua sách tham khảo trước, để dành tiền mua đồ chơi sau",
      "c": "Mua đồ chơi vì thích hơn",
      "d": "Không mua gì cả, tiết kiệm hết",
      "dap_an": "b",
      "giai_thich": "Ưu tiên nhu cầu học tập trước, giải trí sau, phù hợp quản lý tài chính cá nhân."
    },
    {
      "id": 78,
      "dang": "Quản lí tiền",
      "mucdo": "Vận dụng",
      "de": "Bạn Nam thường dùng hết tiền tiêu vặt trong ngày đầu tuần, sau đó phải vay bạn. Em sẽ khuyên Nam điều gì?",
      "a": "Vay thêm nhiều hơn",
      "b": "Lập kế hoạch chi tiêu theo tuần, ghi chép lại",
      "c": "Xin bố mẹ tăng tiền",
      "d": "Bỏ qua, không sao cả",
      "dap_an": "b",
      "giai_thich": "Lập kế hoạch và ghi chép giúp kiểm soát chi tiêu, tránh tình trạng hết tiền sớm."
    },
    {
      "id": 79,
      "dang": "Quản lí tiền",
      "mucdo": "Vận dụng cao",
      "de": "Em muốn mua một chiếc xe đạp mới (giá 1,5 triệu) nhưng bố mẹ chỉ cho 300.000đ/tháng tiêu vặt. Em sẽ lên kế hoạch tiết kiệm như thế nào để đạt mục tiêu?",
      "a": "Nhịn ăn sáng 5 tháng",
      "b": "Xin bố mẹ trả hộ",
      "c": "Lập bảng tiết kiệm: mỗi tháng để ra 150.000đ, kết hợp làm thêm việc nhà được thưởng và kiên trì trong 10 tháng",
      "d": "Bỏ ý định",
      "dap_an": "c",
      "giai_thich": "Lập kế hoạch cụ thể, kiên trì, kết hợp nhiều nguồn nhỏ là quản lý tài chính thông minh."
    },
    {
      "id": 80,
      "dang": "Quản lí tiền",
      "mucdo": "Vận dụng cao",
      "de": "Em thấy một bạn trong lớp thường xuyên mang rất nhiều tiền đi học, khoe của và mua quà cho cả lớp. Hành vi đó có vấn đề gì không?",
      "a": "Tốt, vì bạn hào phóng",
      "b": "Không tốt, vì dễ gây lãng phí, khoe khoang và tạo thói quen chi tiêu không lành mạnh",
      "c": "Bình thường, vì tiền của bạn",
      "d": "Rất đáng khen",
      "dap_an": "b",
      "giai_thich": "Khoe của và tiêu tiền phung phí không phải là quản lý tiền tốt, ảnh hưởng đến giá trị bản thân và quan hệ bạn bè."
    },
    {
      "id": 81,
      "dang": "Phòng, chống tệ nạn xã hội",
      "mucdo": "Nhận biết",
      "de": "Tệ nạn xã hội là gì?",
      "a": "Những hành vi vi phạm pháp luật, lệch chuẩn đạo đức, gây hậu quả xấu",
      "b": "Thói quen ăn mặc cũ kỹ",
      "c": "Những trò chơi dân gian",
      "d": "Các môn thể thao mạo hiểm",
      "dap_an": "a",
      "giai_thich": "Tệ nạn như cờ bạc, ma túy, mại dâm… là hành vi vi phạm pháp luật và đạo đức."
    },
    {
      "id": 82,
      "dang": "Phòng, chống tệ nạn xã hội",
      "mucdo": "Nhận biết",
      "de": "Hành vi nào sau đây là tệ nạn xã hội?",
      "a": "Hút thuốc lá",
      "b": "Sử dụng ma túy",
      "c": "Đi học muộn",
      "d": "Nói chuyện trong lớp",
      "dap_an": "b",
      "giai_thich": "Sử dụng ma túy là tệ nạn nghiêm trọng, bị pháp luật nghiêm cấm."
    },
    {
      "id": 83,
      "dang": "Phòng, chống tệ nạn xã hội",
      "mucdo": "Nhận biết",
      "de": "Tác hại của tệ nạn xã hội đối với học sinh là:",
      "a": "Học tập sa sút, sức khỏe giảm, vi phạm pháp luật",
      "b": "Được nhiều bạn nể",
      "c": "Trở nên giàu có",
      "d": "Tự tin hơn",
      "dap_an": "a",
      "giai_thich": "Tệ nạn hủy hoại tương lai, sức khỏe và nhân cách học sinh."
    },
    {
      "id": 84,
      "dang": "Phòng, chống tệ nạn xã hội",
      "mucdo": "Nhận biết",
      "de": "Để phòng tránh tệ nạn xã hội, học sinh cần:",
      "a": "Sống lành mạnh, không tò mò thử các chất kích thích",
      "b": "Tập hút thuốc cho giống người lớn",
      "c": "Chơi game bạo lực để giải trí",
      "d": "Tham gia các băng nhóm",
      "dap_an": "a",
      "giai_thich": "Lối sống lành mạnh, tránh xa cám dỗ là biện pháp phòng ngừa tốt nhất."
    },
    {
      "id": 85,
      "dang": "Phòng, chống tệ nạn xã hội",
      "mucdo": "Thông hiểu",
      "de": "Vì sao học sinh không nên thử ma túy dù chỉ một lần?",
      "a": "Vì tốn tiền",
      "b": "Vì ma túy dễ gây nghiện, hủy hoại sức khỏe và tương lai",
      "c": "Vì bị bạn bè cười",
      "d": "Vì cha mẹ cấm",
      "dap_an": "b",
      "giai_thich": "Ma túy gây nghiện nhanh chóng, không thể kiểm soát, để lại hậu quả nặng nề."
    },
    {
      "id": 86,
      "dang": "Phòng, chống tệ nạn xã hội",
      "mucdo": "Thông hiểu",
      "de": "Nếu có người lạ rủ em hút thử một điếu thuốc lá 'lạ' và bảo 'rất phê', em sẽ:",
      "a": "Hút thử vì tò mò",
      "b": "Kiên quyết từ chối và bỏ đi, báo cho người lớn nếu thấy khả nghi",
      "c": "Cầm về rồi vứt",
      "d": "Rủ thêm bạn cùng hút",
      "dap_an": "b",
      "giai_thich": "Từ chối dứt khoát và tránh xa nguy cơ, báo người lớn khi cần."
    },
    {
      "id": 87,
      "dang": "Phòng, chống tệ nạn xã hội",
      "mucdo": "Vận dụng",
      "de": "Em phát hiện một người bạn thân có dấu hiệu sử dụng chất gây nghiện. Em nên làm gì?",
      "a": "Giấu không cho ai biết",
      "b": "Cắt đứt quan hệ với bạn",
      "c": "Báo với cha mẹ bạn hoặc thầy cô để giúp bạn cai nghiện kịp thời",
      "d": "Rủ bạn dùng tiếp vì cũng vui",
      "dap_an": "c",
      "giai_thich": "Báo người lớn để giúp bạn chính là cứu bạn, không phải phản bội."
    },
    {
      "id": 88,
      "dang": "Phòng, chống tệ nạn xã hội",
      "mucdo": "Vận dụng",
      "de": "Trên đường đi học về, một nhóm thanh niên chặn em và mời em vào quán điện tử chơi game ăn tiền. Em sẽ:",
      "a": "Vào chơi vì được mời miễn phí",
      "b": "Từ chối khéo và nhanh chóng đi về",
      "c": "Đứng lại xem",
      "d": "Gọi điện khoe bạn",
      "dap_an": "b",
      "giai_thich": "Từ chối và rời khỏi tình huống nguy hiểm, tránh xa cám dỗ."
    },
    {
      "id": 89,
      "dang": "Phòng, chống tệ nạn xã hội",
      "mucdo": "Vận dụng cao",
      "de": "Một người bạn trong lớp rủ em hôm nay nghỉ học để đi chơi và 'thử một cái mới lạ' nhưng không nói rõ là gì. Em sẽ suy luận và xử lý ra sao?",
      "a": "Đi ngay vì vui",
      "b": "Từ chối và khuyên bạn không nên nghỉ học, đồng thời hỏi rõ 'cái mới lạ' đó là gì, nếu nghi ngờ sẽ báo thầy cô",
      "c": "Mặc kệ bạn",
      "d": "Rủ thêm nhiều người cùng đi",
      "dap_an": "b",
      "giai_thich": "Cảnh giác, tìm hiểu thông tin, vừa bảo vệ mình vừa có thể giúp bạn tránh xa tệ nạn."
    },
    {
      "id": 90,
      "dang": "Phòng, chống tệ nạn xã hội",
      "mucdo": "Vận dụng cao",
      "de": "Nhà trường phát động chiến dịch 'Nói không với ma túy'. Em sẽ tham gia bằng hoạt động thiết thực nào dưới đây với tư cách học sinh lớp 7?",
      "a": "Vẽ tranh cổ động, viết bài tuyên truyền, tổ chức sinh hoạt chủ đề trong lớp",
      "b": "Chỉ ký cam kết cho xong",
      "c": "Phát tờ rơi có sẵn",
      "d": "Không tham gia",
      "dap_an": "a",
      "giai_thich": "Vẽ tranh, tuyên truyền sáng tạo phù hợp năng lực và lứa tuổi, lan tỏa thông điệp hiệu quả."
    },
    {
      "id": 91,
      "dang": "Quyền và nghĩa vụ công dân",
      "mucdo": "Nhận biết",
      "de": "Công dân là gì?",
      "a": "Người làm việc cho nhà nước",
      "b": "Người dân của một nước, có quyền và nghĩa vụ theo pháp luật nước đó",
      "c": "Người nước ngoài sinh sống tại Việt Nam",
      "d": "Người giàu có",
      "dap_an": "b",
      "giai_thich": "Công dân có sự gắn bó về mặt pháp lý với một quốc gia."
    },
    {
      "id": 92,
      "dang": "Quyền và nghĩa vụ công dân",
      "mucdo": "Nhận biết",
      "de": "Quyền cơ bản của công dân được ghi nhận ở đâu?",
      "a": "Sách giáo khoa",
      "b": "Lời nói của Tổng thống",
      "c": "Hiến pháp và pháp luật",
      "d": "Truyền thống gia đình",
      "dap_an": "c",
      "giai_thich": "Hiến pháp là luật cơ bản, quy định các quyền và nghĩa vụ của công dân."
    },
    {
      "id": 93,
      "dang": "Quyền và nghĩa vụ công dân",
      "mucdo": "Nhận biết",
      "de": "Nghĩa vụ của công dân đối với Tổ quốc là gì?",
      "a": "Bảo vệ Tổ quốc, tuân thủ Hiến pháp và pháp luật",
      "b": "Chỉ đóng thuế",
      "c": "Đi du lịch nước ngoài",
      "d": "Học tập suốt đời",
      "dap_an": "a",
      "giai_thich": "Bảo vệ Tổ quốc và tuân thủ pháp luật là nghĩa vụ thiêng liêng."
    },
    {
      "id": 94,
      "dang": "Quyền và nghĩa vụ công dân",
      "mucdo": "Nhận biết",
      "de": "Trẻ em có những quyền gì?",
      "a": "Quyền được khai sinh, học tập, vui chơi, chăm sóc sức khỏe",
      "b": "Quyền tự do vô hạn",
      "c": "Quyền không phải làm việc gì",
      "d": "Quyền bỏ học khi không thích",
      "dap_an": "a",
      "giai_thich": "Theo Công ước Liên Hợp Quốc và Luật Trẻ em, trẻ em có các quyền cơ bản đó."
    },
    {
      "id": 95,
      "dang": "Quyền và nghĩa vụ công dân",
      "mucdo": "Thông hiểu",
      "de": "Vì sao học sinh lớp 7 cần biết về quyền và nghĩa vụ của công dân?",
      "a": "Để sau này làm quan",
      "b": "Để biết cách bảo vệ mình và thực hiện đúng bổn phận",
      "c": "Để đi kiện người khác",
      "d": "Để khỏi bị phạt",
      "dap_an": "b",
      "giai_thich": "Hiểu biết về quyền và nghĩa vụ giúp học sinh có ý thức công dân, tự bảo vệ và thực hiện bổn phận."
    },
    {
      "id": 96,
      "dang": "Quyền và nghĩa vụ công dân",
      "mucdo": "Thông hiểu",
      "de": "Cha mẹ không cho em đi học vì nhà nghèo. Điều đó vi phạm quyền gì của em?",
      "a": "Quyền được chăm sóc sức khỏe",
      "b": "Quyền được vui chơi",
      "c": "Quyền được học tập",
      "d": "Quyền được làm việc",
      "dap_an": "c",
      "giai_thich": "Học tập là quyền cơ bản của trẻ em, không ai được tước đoạt."
    },
    {
      "id": 97,
      "dang": "Quyền và nghĩa vụ công dân",
      "mucdo": "Vận dụng",
      "de": "Em nhìn thấy một bạn trong xóm bị bố mẹ đánh đập, nhốt trong nhà không cho đi học. Em sẽ làm gì?",
      "a": "Làm ngơ, việc nhà người ta",
      "b": "Báo với chính quyền địa phương hoặc đường dây bảo vệ trẻ em",
      "c": "Vào can ngăn trực tiếp",
      "d": "Kể cho bạn bè nghe",
      "dap_an": "b",
      "giai_thich": "Báo cơ quan chức năng là cách bảo vệ quyền trẻ em đúng đắn, an toàn."
    },
    {
      "id": 98,
      "dang": "Quyền và nghĩa vụ công dân",
      "mucdo": "Vận dụng",
      "de": "Em được sinh ra ở Việt Nam, bố mẹ đều là người Việt. Em có quốc tịch nào?",
      "a": "Quốc tịch nước ngoài",
      "b": "Quốc tịch Việt Nam",
      "c": "Không có quốc tịch",
      "d": "Quốc tịch tự chọn",
      "dap_an": "b",
      "giai_thich": "Theo Luật Quốc tịch, trẻ sinh ra ở Việt Nam có bố mẹ Việt Nam thì có quốc tịch Việt Nam."
    },
    {
      "id": 99,
      "dang": "Quyền và nghĩa vụ công dân",
      "mucdo": "Vận dụng cao",
      "de": "Trong giờ ra chơi, một nhóm học sinh đánh em vì lý do không đáng. Hành vi đó xâm phạm quyền gì của em? Em sẽ làm gì để bảo vệ quyền đó?",
      "a": "Quyền được bảo vệ sức khỏe, tính mạng, danh dự. Em sẽ báo với thầy cô, gia đình và yêu cầu nhà trường xử lý",
      "b": "Quyền học tập. Em sẽ đánh trả",
      "c": "Quyền vui chơi. Em sẽ bỏ chạy",
      "d": "Quyền tự do ngôn luận. Em sẽ im lặng",
      "dap_an": "a",
      "giai_thich": "Đánh đập xâm phạm quyền được bảo vệ thân thể, sức khỏe. Học sinh cần báo với người lớn để bảo vệ quyền hợp pháp."
    },
    {
      "id": 100,
      "dang": "Quyền và nghĩa vụ công dân",
      "mucdo": "Vận dụng cao",
      "de": "Em biết một người hàng xóm thường xuyên chửi bới, đánh đập con cái. Em có thể làm gì trong khuôn khổ pháp luật và phù hợp với lứa tuổi để bảo vệ quyền của các bạn nhỏ?",
      "a": "Kể với bố mẹ em, cùng bố mẹ báo với tổ dân phố hoặc công an xã",
      "b": "Đến nhà họ và cãi nhau",
      "c": "Đăng lên mạng xã hội nói xấu",
      "d": "Không quan tâm vì không phải việc của mình",
      "dap_an": "a",
      "giai_thich": "Hành động trong vòng tay người lớn, báo chính quyền là cách đúng đắn, an toàn và hiệu quả để bảo vệ quyền trẻ em."
    }
  ]
}